ReversingLabs/__init__.py
ReversingLabs/SDK/__init__.py
ReversingLabs/SDK/a1000.py
ReversingLabs/SDK/helper.py
ReversingLabs/SDK/ticloud.py
ReversingLabs/SDK/tiscale.py
reversinglabs_sdk_py2-1.2.1.dist-info/LICENSE
reversinglabs_sdk_py2-1.2.1.dist-info/METADATA
reversinglabs_sdk_py2-1.2.1.dist-info/WHEEL
reversinglabs_sdk_py2-1.2.1.dist-info/top_level.txt
reversinglabs_sdk_py2-1.2.1.dist-info/RECORD
