Metadata-Version: 2.1
Name: reversinglabs-sdk-py2
Version: 1.2.1
Summary: Python SDK for using ReversingLabs services - Python 2 version.
Home-page: https://github.com/reversinglabs/reversinglabs-sdk-py2
Author: ReversingLabs
Author-email: support@reversinglabs.com
License: MIT
Project-URL: Source, https://github.com/reversinglabs/reversinglabs-sdk-py2
Project-URL: Documentation, https://github.com/reversinglabs/reversinglabs-sdk-py2/blob/main/README.md
Platform: UNKNOWN
Classifier: Development Status :: 5 - Production/Stable
Classifier: Intended Audience :: Developers
Classifier: Natural Language :: English
Classifier: Programming Language :: Python
Classifier: Programming Language :: Python :: 2
Classifier: Programming Language :: Python :: 2.7
Classifier: Programming Language :: Python :: Implementation :: CPython
Classifier: Topic :: Security
Classifier: Topic :: Software Development :: Libraries :: Python Modules
Requires-Python: >=2.7
Requires-Dist: requests
